{"dateObj":"20/11/2019 07:14:10","totalMsgsObj":9,"totalMsgsMiniMongoObj":9,"domDurationObj":0.001,"miniMongoDurationObj":0,"metricsObj":{"Timestamp":37105.911215,"Documents":1,"Frames":1,"JSEventListeners":215,"Nodes":889,"LayoutCount":43,"RecalcStyleCount":78,"LayoutDuration":0.152413,"RecalcStyleDuration":0.139186,"ScriptDuration":0.876327,"TaskDuration":1.651213,"JSHeapUsedSize":21864616,"JSHeapTotalSize":60862464},"performancesObj":{"timeOrigin":1574288045417.7097,"timing":{"navigationStart":1574288045417,"unloadEventStart":1574288045754,"unloadEventEnd":1574288045754,"redirectStart":1574288045418,"redirectEnd":1574288045586,"fetchStart":1574288045586,"domainLookupStart":1574288045586,"domainLookupEnd":1574288045586,"connectStart":1574288045586,"connectEnd":1574288045586,"secureConnectionStart":0,"requestStart":1574288045588,"responseStart":1574288045752,"responseEnd":1574288045753,"domLoading":1574288045757,"domInteractive":1574288047761,"domContentLoadedEventStart":1574288047761,"domContentLoadedEventEnd":1574288047786,"domComplete":1574288047981,"loadEventStart":1574288047981,"loadEventEnd":1574288047981},"navigation":{"type":0,"redirectCount":1}}}
{"dateObj":"20/11/2019 07:15:10","totalMsgsObj":9,"totalMsgsMiniMongoObj":9,"domDurationObj":0.004,"miniMongoDurationObj":0,"metricsObj":{"Timestamp":37165.939209,"Documents":2,"Frames":2,"JSEventListeners":199,"Nodes":5288,"LayoutCount":50,"RecalcStyleCount":101,"LayoutDuration":0.163262,"RecalcStyleDuration":0.159147,"ScriptDuration":1.062478,"TaskDuration":2.329405,"JSHeapUsedSize":20755088,"JSHeapTotalSize":23638016},"performancesObj":{"timeOrigin":1574288045417.7097,"timing":{"navigationStart":1574288045417,"unloadEventStart":1574288045754,"unloadEventEnd":1574288045754,"redirectStart":1574288045418,"redirectEnd":1574288045586,"fetchStart":1574288045586,"domainLookupStart":1574288045586,"domainLookupEnd":1574288045586,"connectStart":1574288045586,"connectEnd":1574288045586,"secureConnectionStart":0,"requestStart":1574288045588,"responseStart":1574288045752,"responseEnd":1574288045753,"domLoading":1574288045757,"domInteractive":1574288047761,"domContentLoadedEventStart":1574288047761,"domContentLoadedEventEnd":1574288047786,"domComplete":1574288047981,"loadEventStart":1574288047981,"loadEventEnd":1574288047981},"navigation":{"type":0,"redirectCount":1}}}
{"dateObj":"20/11/2019 07:16:10","totalMsgsObj":9,"totalMsgsMiniMongoObj":9,"domDurationObj":0.004,"miniMongoDurationObj":0,"metricsObj":{"Timestamp":37225.964467,"Documents":2,"Frames":2,"JSEventListeners":202,"Nodes":5318,"LayoutCount":55,"RecalcStyleCount":106,"LayoutDuration":0.168227,"RecalcStyleDuration":0.162286,"ScriptDuration":1.144302,"TaskDuration":2.63445,"JSHeapUsedSize":21407648,"JSHeapTotalSize":23900160},"performancesObj":{"timeOrigin":1574288045417.7097,"timing":{"navigationStart":1574288045417,"unloadEventStart":1574288045754,"unloadEventEnd":1574288045754,"redirectStart":1574288045418,"redirectEnd":1574288045586,"fetchStart":1574288045586,"domainLookupStart":1574288045586,"domainLookupEnd":1574288045586,"connectStart":1574288045586,"connectEnd":1574288045586,"secureConnectionStart":0,"requestStart":1574288045588,"responseStart":1574288045752,"responseEnd":1574288045753,"domLoading":1574288045757,"domInteractive":1574288047761,"domContentLoadedEventStart":1574288047761,"domContentLoadedEventEnd":1574288047786,"domComplete":1574288047981,"loadEventStart":1574288047981,"loadEventEnd":1574288047981},"navigation":{"type":0,"redirectCount":1}}}
{"dateObj":"20/11/2019 07:17:10","totalMsgsObj":9,"totalMsgsMiniMongoObj":9,"domDurationObj":0.001,"miniMongoDurationObj":0,"metricsObj":{"Timestamp":37285.974751,"Documents":2,"Frames":2,"JSEventListeners":205,"Nodes":5348,"LayoutCount":60,"RecalcStyleCount":111,"LayoutDuration":0.171821,"RecalcStyleDuration":0.165211,"ScriptDuration":1.287071,"TaskDuration":3.005457,"JSHeapUsedSize":21914576,"JSHeapTotalSize":24686592},"performancesObj":{"timeOrigin":1574288045417.7097,"timing":{"navigationStart":1574288045417,"unloadEventStart":1574288045754,"unloadEventEnd":1574288045754,"redirectStart":1574288045418,"redirectEnd":1574288045586,"fetchStart":1574288045586,"domainLookupStart":1574288045586,"domainLookupEnd":1574288045586,"connectStart":1574288045586,"connectEnd":1574288045586,"secureConnectionStart":0,"requestStart":1574288045588,"responseStart":1574288045752,"responseEnd":1574288045753,"domLoading":1574288045757,"domInteractive":1574288047761,"domContentLoadedEventStart":1574288047761,"domContentLoadedEventEnd":1574288047786,"domComplete":1574288047981,"loadEventStart":1574288047981,"loadEventEnd":1574288047981},"navigation":{"type":0,"redirectCount":1}}}
{"dateObj":"20/11/2019 07:18:10","totalMsgsObj":9,"totalMsgsMiniMongoObj":9,"domDurationObj":0.003,"miniMongoDurationObj":0,"metricsObj":{"Timestamp":37345.995092,"Documents":2,"Frames":2,"JSEventListeners":208,"Nodes":5378,"LayoutCount":65,"RecalcStyleCount":116,"LayoutDuration":0.177103,"RecalcStyleDuration":0.168383,"ScriptDuration":1.37031,"TaskDuration":3.301636,"JSHeapUsedSize":22367080,"JSHeapTotalSize":25210880},"performancesObj":{"timeOrigin":1574288045417.7097,"timing":{"navigationStart":1574288045417,"unloadEventStart":1574288045754,"unloadEventEnd":1574288045754,"redirectStart":1574288045418,"redirectEnd":1574288045586,"fetchStart":1574288045586,"domainLookupStart":1574288045586,"domainLookupEnd":1574288045586,"connectStart":1574288045586,"connectEnd":1574288045586,"secureConnectionStart":0,"requestStart":1574288045588,"responseStart":1574288045752,"responseEnd":1574288045753,"domLoading":1574288045757,"domInteractive":1574288047761,"domContentLoadedEventStart":1574288047761,"domContentLoadedEventEnd":1574288047786,"domComplete":1574288047981,"loadEventStart":1574288047981,"loadEventEnd":1574288047981},"navigation":{"type":0,"redirectCount":1}}}
